[
  {
    "key": "1001",
    "values": [
      {
        "teamid": "1001",
        "method": "public_transport",
        "start": "2015-02-03T10:59:34.000Z",
        "end": "2015-02-03T11:00:01.000Z",
        "distance": 0.33471076009940803
      },
      {
        "teamid": "1001",
        "method": "walking",
        "start": "2015-02-03T11:00:52.993Z",
        "end": "2015-02-03T11:01:49.000Z",
        "distance": 0.40457818610470647
      },
      {
        "teamid": "1001",
        "method": "walking",
        "start": "2015-02-03T11:02:00.553Z",
        "end": "2015-02-03T11:03:29.000Z",
        "distance": 0.3597953566135229
      },
      {
        "teamid": "1001",
        "method": "walking",
        "start": "2015-02-03T11:05:03.844Z",
        "end": "2015-02-03T11:09:16.000Z",
        "distance": 0.37757342237257224
      },
      {
        "teamid": "1001",
        "method": "walking",
        "start": "2015-02-03T11:37:43.223Z",
        "end": "2015-02-03T11:41:14.000Z",
        "distance": 0.30339551872813353
      },
      {
        "teamid": "1001",
        "method": "public_transport",
        "start": "2015-02-04T06:32:49.434Z",
        "end": "2015-02-04T06:33:43.000Z",
        "distance": 1.9282603430379197
      },
      {
        "teamid": "1001",
        "method": "public_transport",
        "start": "2015-02-04T06:41:17.230Z",
        "end": "2015-02-04T06:45:43.000Z",
        "distance": 7.079317291377607
      },
      {
        "teamid": "1001",
        "method": "public_transport",
        "start": "2015-02-04T06:45:59.069Z",
        "end": "2015-02-04T06:52:14.000Z",
        "distance": 66.25834254555878
      },
      {
        "teamid": "1001",
        "method": "walking",
        "start": "2015-02-04T07:01:36.919Z",
        "end": "2015-02-04T07:02:39.426Z",
        "distance": 1.8333849373301985
      },
      {
        "teamid": "1001",
        "method": "walking",
        "start": "2015-02-04T09:18:09.756Z",
        "end": "2015-02-04T09:35:39.000Z",
        "distance": 13.185340615087616
      }
    ]
  },
  {
    "key": "1003",
    "values": [
      {
        "teamid": "1003",
        "method": "public_transport",
        "start": "2015-02-05T11:58:40.539Z",
        "end": "2015-02-05T12:17:41.025Z",
        "distance": 99.76591838825897
      },
      {
        "teamid": "1003",
        "method": "public_transport",
        "start": "2015-02-05T12:10:31.879Z",
        "end": "2015-02-05T12:45:49.000Z",
        "distance": 24.99969534835399
      },
      {
        "teamid": "1003",
        "method": "walking",
        "start": "2015-02-05T12:47:19.901Z",
        "end": "2015-02-05T12:55:48.000Z",
        "distance": 0.8074411267730716
      }
    ]
  },
  {
    "key": "1004",
    "values": [
      {
        "teamid": "1004",
        "method": "walking",
        "start": "2015-02-02T11:35:53.044Z",
        "end": "2015-02-02T12:41:43.732Z",
        "distance": 3.589221925862908
      },
      {
        "teamid": "1004",
        "method": "walking",
        "start": "2015-02-04T13:17:57.823Z",
        "end": "2015-02-04T13:31:05.140Z",
        "distance": 1.6366121720268483
      },
      {
        "teamid": "1004",
        "method": "walking",
        "start": "2015-02-04T14:03:17.145Z",
        "end": "2015-02-04T14:08:44.157Z",
        "distance": 0.8774730888148012
      }
    ]
  },
  {
    "key": "1012",
    "values": [
      {
        "teamid": "1012",
        "method": "public_transport",
        "start": "2015-02-02T10:00:21.239Z",
        "end": "2015-02-02T10:05:02.166Z",
        "distance": 0.8259463331846908
      },
      {
        "teamid": "1012",
        "method": "walking",
        "start": "2015-02-02T11:39:50.323Z",
        "end": "2015-02-02T11:55:49.631Z",
        "distance": 1.4825830250257543
      },
      {
        "teamid": "1012",
        "method": "public_transport",
        "start": "2015-02-02T11:56:45.601Z",
        "end": "2015-02-02T11:58:50.633Z",
        "distance": 0.46646292073942813
      },
      {
        "teamid": "1012",
        "method": "walking",
        "start": "2015-02-02T12:05:33.077Z",
        "end": "2015-02-02T12:13:38.052Z",
        "distance": 8.36612988355332
      },
      {
        "teamid": "1012",
        "method": "public_transport",
        "start": "2015-02-03T11:02:23.799Z",
        "end": "2015-02-03T11:22:38.914Z",
        "distance": 3.4172403861599423
      },
      {
        "teamid": "1012",
        "method": "public_transport",
        "start": "2015-02-04T06:46:54.250Z",
        "end": "2015-02-04T06:49:26.200Z",
        "distance": 8.244257624185867
      },
      {
        "teamid": "1012",
        "method": "public_transport",
        "start": "2015-02-04T11:14:26.966Z",
        "end": "2015-02-04T11:19:52.357Z",
        "distance": 1.4441242008918862
      },
      {
        "teamid": "1012",
        "method": "walking",
        "start": "2015-02-04T11:19:58.270Z",
        "end": "2015-02-04T11:23:46.286Z",
        "distance": 0.3394147566756211
      }
    ]
  },
  {
    "key": "1020",
    "values": [
      {
        "teamid": "1020",
        "method": "public_transport",
        "start": "2015-02-04T14:45:01.336Z",
        "end": "2015-02-04T14:46:36.966Z",
        "distance": 1.5650924262564
      }
    ]
  },
  {
    "key": "1021",
    "values": [
      {
        "teamid": "1021",
        "method": "public_transport",
        "start": "2015-02-02T12:04:08.753Z",
        "end": "2015-02-02T12:18:21.626Z",
        "distance": 6.521700433035755
      },
      {
        "teamid": "1021",
        "method": "public_transport",
        "start": "2015-02-02T13:56:09.510Z",
        "end": "2015-02-02T14:00:43.051Z",
        "distance": 3.8759737075622613
      },
      {
        "teamid": "1021",
        "method": "public_transport",
        "start": "2015-02-02T14:00:53.177Z",
        "end": "2015-02-02T14:03:43.343Z",
        "distance": 1.5444766042834912
      },
      {
        "teamid": "1021",
        "method": "public_transport",
        "start": "2015-02-02T14:03:55.381Z",
        "end": "2015-02-02T14:09:28.331Z",
        "distance": 2.7062440388827746
      },
      {
        "teamid": "1021",
        "method": "walking",
        "start": "2015-02-02T14:15:02.066Z",
        "end": "2015-02-02T15:10:46.022Z",
        "distance": 5.129962928205006
      },
      {
        "teamid": "1021",
        "method": "public_transport",
        "start": "2015-02-03T10:24:10.458Z",
        "end": "2015-02-03T10:35:11.669Z",
        "distance": 7.35604125110658
      },
      {
        "teamid": "1021",
        "method": "public_transport",
        "start": "2015-02-03T10:35:23.621Z",
        "end": "2015-02-03T11:11:13.606Z",
        "distance": 11.984386043636064
      }
    ]
  },
  {
    "key": "1027",
    "values": [
      {
        "teamid": "1027",
        "method": "walking",
        "start": "2015-02-02T09:50:37.878Z",
        "end": "2015-02-02T10:41:27.057Z",
        "distance": 7.1947669317348275
      },
      {
        "teamid": "1027",
        "method": "walking",
        "start": "2015-02-02T09:50:54.935Z",
        "end": "2015-02-02T10:40:59.487Z",
        "distance": 7.282124408237006
      },
      {
        "teamid": "1027",
        "method": "public_transport",
        "start": "2015-02-02T09:53:20.131Z",
        "end": "2015-02-02T10:47:54.885Z",
        "distance": 7.048111571613317
      },
      {
        "teamid": "1027",
        "method": "walking",
        "start": "2015-02-02T09:54:09.532Z",
        "end": "2015-02-02T13:46:02.458Z",
        "distance": 20.523901890908387
      },
      {
        "teamid": "1027",
        "method": "public_transport",
        "start": "2015-02-03T07:50:56.524Z",
        "end": "2015-02-03T08:27:09.903Z",
        "distance": 11.336087458861735
      },
      {
        "teamid": "1027",
        "method": "public_transport",
        "start": "2015-02-03T13:29:35.348Z",
        "end": "2015-02-03T13:31:55.424Z",
        "distance": 0.9828566614859464
      }
    ]
  },
  {
    "key": "1028",
    "values": [
      {
        "teamid": "1028",
        "method": "walking",
        "start": "2015-02-05T10:55:28.327Z",
        "end": "2015-02-05T10:59:56.000Z",
        "distance": 1.5498592434658696
      }
    ]
  },
  {
    "key": "1032",
    "values": [
      {
        "teamid": "1032",
        "method": "public_transport",
        "start": "2015-02-02T14:01:55.471Z",
        "end": "2015-02-02T14:10:25.809Z",
        "distance": 6.440120883588352
      },
      {
        "teamid": "1032",
        "method": "public_transport",
        "start": "2015-02-03T09:08:59.311Z",
        "end": "2015-02-03T09:10:26.053Z",
        "distance": 0.7837538055819859
      },
      {
        "teamid": "1032",
        "method": "walking",
        "start": "2015-02-03T09:10:56.989Z",
        "end": "2015-02-03T09:13:30.035Z",
        "distance": 0.28466487879473723
      },
      {
        "teamid": "1032",
        "method": "public_transport",
        "start": "2015-02-03T09:20:20.577Z",
        "end": "2015-02-03T09:33:16.933Z",
        "distance": 3.307352616968764
      }
    ]
  },
  {
    "key": "1033",
    "values": [
      {
        "teamid": "1033",
        "method": "walking",
        "start": "2015-02-03T11:42:04.000Z",
        "end": "2015-02-03T11:45:41.000Z",
        "distance": 0.23559530683370125
      }
    ]
  },
  {
    "key": "1034",
    "values": [
      {
        "teamid": "1034",
        "method": "walking",
        "start": "2015-02-03T15:51:24.656Z",
        "end": "2015-02-03T15:54:32.066Z",
        "distance": 0.24728908002651298
      },
      {
        "teamid": "1034",
        "method": "public_transport",
        "start": "2015-02-03T16:17:35.494Z",
        "end": "2015-02-03T16:18:05.051Z",
        "distance": 0.45421416042483737
      },
      {
        "teamid": "1034",
        "method": "public_transport",
        "start": "2015-02-03T16:18:17.817Z",
        "end": "2015-02-03T16:19:17.081Z",
        "distance": 0.34277248407737143
      },
      {
        "teamid": "1034",
        "method": "public_transport",
        "start": "2015-02-03T16:19:23.981Z",
        "end": "2015-02-03T16:20:50.069Z",
        "distance": 0.7123719413199452
      },
      {
        "teamid": "1034",
        "method": "public_transport",
        "start": "2015-02-03T16:29:23.910Z",
        "end": "2015-02-03T16:30:14.056Z",
        "distance": 0.5329340047240931
      },
      {
        "teamid": "1034",
        "method": "public_transport",
        "start": "2015-02-03T16:30:28.063Z",
        "end": "2015-02-03T16:30:51.056Z",
        "distance": 0.34315952457897403
      },
      {
        "teamid": "1034",
        "method": "public_transport",
        "start": "2015-02-03T16:31:44.578Z",
        "end": "2015-02-03T16:31:55.055Z",
        "distance": 0.2311229620148004
      },
      {
        "teamid": "1034",
        "method": "public_transport",
        "start": "2015-02-03T16:32:01.389Z",
        "end": "2015-02-03T16:32:25.051Z",
        "distance": 0.2322450350791157
      },
      {
        "teamid": "1034",
        "method": "public_transport",
        "start": "2015-02-03T16:32:29.713Z",
        "end": "2015-02-03T16:33:02.055Z",
        "distance": 0.2801770947603175
      },
      {
        "teamid": "1034",
        "method": "public_transport",
        "start": "2015-02-03T16:35:05.064Z",
        "end": "2015-02-03T16:35:32.048Z",
        "distance": 0.4215067319831252
      },
      {
        "teamid": "1034",
        "method": "public_transport",
        "start": "2015-02-04T07:24:35.708Z",
        "end": "2015-02-04T07:48:17.074Z",
        "distance": 11.167698904981368
      },
      {
        "teamid": "1034",
        "method": "public_transport",
        "start": "2015-02-04T07:48:28.987Z",
        "end": "2015-02-04T07:49:55.075Z",
        "distance": 1.7458337579647107
      }
    ]
  },
  {
    "key": "1038",
    "values": [
      {
        "teamid": "1038",
        "method": "walking",
        "start": "2015-02-03T12:39:56.112Z",
        "end": "2015-02-03T12:50:51.163Z",
        "distance": 12.838947519508741
      },
      {
        "teamid": "1038",
        "method": "public_transport",
        "start": "2015-02-04T09:03:33.039Z",
        "end": "2015-02-04T09:13:39.121Z",
        "distance": 13.376506502733
      },
      {
        "teamid": "1038",
        "method": "public_transport",
        "start": "2015-02-04T09:16:17.134Z",
        "end": "2015-02-04T09:22:22.122Z",
        "distance": 2.9330481203575363
      }
    ]
  },
  {
    "key": "1041",
    "values": [
      {
        "teamid": "1041",
        "method": "walking",
        "start": "2015-02-02T10:12:29.010Z",
        "end": "2015-02-02T11:18:05.767Z",
        "distance": 1.9664424418651862
      }
    ]
  },
  {
    "key": "1045",
    "values": [
      {
        "teamid": "1045",
        "method": "walking",
        "start": "2015-02-02T11:50:50.979Z",
        "end": "2015-02-02T12:02:21.652Z",
        "distance": 2.190905886342831
      },
      {
        "teamid": "1045",
        "method": "walking",
        "start": "2015-02-02T12:02:32.494Z",
        "end": "2015-02-02T12:32:23.662Z",
        "distance": 1.4437686174004756
      },
      {
        "teamid": "1045",
        "method": "public_transport",
        "start": "2015-02-02T12:32:29.851Z",
        "end": "2015-02-02T12:38:47.670Z",
        "distance": 1.211379606816947
      },
      {
        "teamid": "1045",
        "method": "walking",
        "start": "2015-02-02T12:38:53.467Z",
        "end": "2015-02-02T12:43:43.666Z",
        "distance": 0.3000734240943097
      }
    ]
  },
  {
    "key": "1049",
    "values": [
      {
        "teamid": "1049",
        "method": "public_transport",
        "start": "2015-02-02T10:23:59.408Z",
        "end": "2015-02-02T10:31:25.803Z",
        "distance": 2.5937198712894807
      }
    ]
  },
  {
    "key": "1052",
    "values": [
      {
        "teamid": "1052",
        "method": "public_transport",
        "start": "2015-02-05T11:12:29.038Z",
        "end": "2015-02-05T11:29:08.048Z",
        "distance": 5.486568788468237
      }
    ]
  },
  {
    "key": "1055",
    "values": [
      {
        "teamid": "1055",
        "method": "walking",
        "start": "2015-02-02T15:01:44.770Z",
        "end": "2015-02-02T15:02:09.082Z",
        "distance": 0.4032247162487778
      },
      {
        "teamid": "1055",
        "method": "walking",
        "start": "2015-02-02T16:15:57.000Z",
        "end": "2015-02-02T16:37:25.000Z",
        "distance": 23.44675416284194
      },
      {
        "teamid": "1055",
        "method": "walking",
        "start": "2015-02-02T16:16:37.531Z",
        "end": "2015-02-02T16:37:26.228Z",
        "distance": 8.696990407807357
      },
      {
        "teamid": "1055",
        "method": "walking",
        "start": "2015-02-03T14:02:05.761Z",
        "end": "2015-02-03T14:02:24.793Z",
        "distance": 0.21117813977157815
      },
      {
        "teamid": "1055",
        "method": "walking",
        "start": "2015-02-03T14:02:34.833Z",
        "end": "2015-02-03T14:02:49.953Z",
        "distance": 0.22880080918613513
      },
      {
        "teamid": "1055",
        "method": "walking",
        "start": "2015-02-03T14:02:58.002Z",
        "end": "2015-02-03T14:03:33.931Z",
        "distance": 0.2135041025442009
      },
      {
        "teamid": "1055",
        "method": "walking",
        "start": "2015-02-03T14:04:00.919Z",
        "end": "2015-02-03T14:04:14.879Z",
        "distance": 0.2154530906828096
      },
      {
        "teamid": "1055",
        "method": "walking",
        "start": "2015-02-04T07:32:46.179Z",
        "end": "2015-02-04T07:41:09.383Z",
        "distance": 0.4659702732147588
      },
      {
        "teamid": "1055",
        "method": "walking",
        "start": "2015-02-04T16:14:13.776Z",
        "end": "2015-02-04T16:14:54.835Z",
        "distance": 0.28389066791956835
      },
      {
        "teamid": "1055",
        "method": "walking",
        "start": "2015-02-04T16:14:59.294Z",
        "end": "2015-02-04T16:16:44.837Z",
        "distance": 0.2085748311932859
      },
      {
        "teamid": "1055",
        "method": "walking",
        "start": "2015-02-04T16:16:49.260Z",
        "end": "2015-02-04T16:18:51.836Z",
        "distance": 0.2434633846587494
      },
      {
        "teamid": "1055",
        "method": "walking",
        "start": "2015-02-04T19:58:45.900Z",
        "end": "2015-02-04T19:59:09.734Z",
        "distance": 0.5547857568311392
      },
      {
        "teamid": "1055",
        "method": "walking",
        "start": "2015-02-04T20:14:07.990Z",
        "end": "2015-02-04T20:14:25.995Z",
        "distance": 0.7679363697217452
      },
      {
        "teamid": "1055",
        "method": "walking",
        "start": "2015-02-04T20:15:38.700Z",
        "end": "2015-02-04T20:16:06.141Z",
        "distance": 1.4330678430875217
      },
      {
        "teamid": "1055",
        "method": "public_transport",
        "start": "2015-02-05T08:15:44.886Z",
        "end": "2015-02-05T08:20:20.850Z",
        "distance": 11.119299486584127
      },
      {
        "teamid": "1055",
        "method": "public_transport",
        "start": "2015-02-05T08:15:50.989Z",
        "end": "2015-02-05T08:33:28.351Z",
        "distance": 42.67586682760565
      },
      {
        "teamid": "1055",
        "method": "public_transport",
        "start": "2015-02-05T08:20:31.842Z",
        "end": "2015-02-05T08:21:44.885Z",
        "distance": 0.6762375212003996
      }
    ]
  },
  {
    "key": "1057",
    "values": [
      {
        "teamid": "1057",
        "method": "walking",
        "start": "2015-02-02T10:31:21.921Z",
        "end": "2015-02-02T13:08:16.051Z",
        "distance": 12.60497754913137
      },
      {
        "teamid": "1057",
        "method": "walking",
        "start": "2015-02-02T10:31:50.726Z",
        "end": "2015-02-02T11:16:48.688Z",
        "distance": 10.494272263039498
      },
      {
        "teamid": "1057",
        "method": "walking",
        "start": "2015-02-02T11:17:27.123Z",
        "end": "2015-02-02T11:52:15.496Z",
        "distance": 3.3600809073426077
      },
      {
        "teamid": "1057",
        "method": "public_transport",
        "start": "2015-02-03T10:57:48.836Z",
        "end": "2015-02-03T11:15:08.397Z",
        "distance": 3.799829596520028
      },
      {
        "teamid": "1057",
        "method": "public_transport",
        "start": "2015-02-05T10:11:57.967Z",
        "end": "2015-02-05T10:15:36.489Z",
        "distance": 5.638874093876945
      },
      {
        "teamid": "1057",
        "method": "public_transport",
        "start": "2015-02-05T10:16:07.732Z",
        "end": "2015-02-05T10:17:03.805Z",
        "distance": 1.5029715133312072
      },
      {
        "teamid": "1057",
        "method": "walking",
        "start": "2015-02-05T10:17:12.376Z",
        "end": "2015-02-05T10:19:41.300Z",
        "distance": 0.20912785348630294
      },
      {
        "teamid": "1057",
        "method": "walking",
        "start": "2015-02-05T10:28:04.460Z",
        "end": "2015-02-05T10:30:19.683Z",
        "distance": 0.21661364835784058
      },
      {
        "teamid": "1057",
        "method": "public_transport",
        "start": "2015-02-05T15:46:42.271Z",
        "end": "2015-02-05T15:48:52.888Z",
        "distance": 0.6354530174439202
      },
      {
        "teamid": "1057",
        "method": "walking",
        "start": "2015-02-05T15:46:53.938Z",
        "end": "2015-02-05T15:47:25.771Z",
        "distance": 0.20910554213767102
      },
      {
        "teamid": "1057",
        "method": "public_transport",
        "start": "2015-02-05T15:48:41.003Z",
        "end": "2015-02-05T15:51:09.789Z",
        "distance": 0.3838007186328258
      },
      {
        "teamid": "1057",
        "method": "public_transport",
        "start": "2015-02-05T15:49:21.433Z",
        "end": "2015-02-05T15:54:25.644Z",
        "distance": 0.6256130263206079
      },
      {
        "teamid": "1057",
        "method": "public_transport",
        "start": "2015-02-05T15:54:48.451Z",
        "end": "2015-02-05T15:58:03.188Z",
        "distance": 0.5333926477936067
      }
    ]
  },
  {
    "key": "1060",
    "values": [
      {
        "teamid": "1060",
        "method": "public_transport",
        "start": "2015-02-02T13:07:10.263Z",
        "end": "2015-02-02T13:13:44.693Z",
        "distance": 1.447378040086527
      },
      {
        "teamid": "1060",
        "method": "walking",
        "start": "2015-02-04T07:33:12.802Z",
        "end": "2015-02-04T07:46:35.458Z",
        "distance": 14.442811114769247
      }
    ]
  },
  {
    "key": "1062",
    "values": [
      {
        "teamid": "1062",
        "method": "public_transport",
        "start": "2015-02-03T13:35:02.399Z",
        "end": "2015-02-03T13:38:48.267Z",
        "distance": 15.19610820221859
      }
    ]
  },
  {
    "key": "1064",
    "values": [
      {
        "teamid": "1064",
        "method": "walking",
        "start": "2015-02-03T13:19:52.193Z",
        "end": "2015-02-03T13:23:22.132Z",
        "distance": 0.7250918256086681
      },
      {
        "teamid": "1064",
        "method": "public_transport",
        "start": "2015-02-03T13:24:49.160Z",
        "end": "2015-02-03T13:30:38.126Z",
        "distance": 1.867220552524302
      },
      {
        "teamid": "1064",
        "method": "walking",
        "start": "2015-02-03T13:30:48.133Z",
        "end": "2015-02-03T13:37:27.154Z",
        "distance": 0.6672571371859766
      },
      {
        "teamid": "1064",
        "method": "walking",
        "start": "2015-02-03T13:45:26.571Z",
        "end": "2015-02-03T13:54:01.135Z",
        "distance": 0.9771517248801144
      },
      {
        "teamid": "1064",
        "method": "public_transport",
        "start": "2015-02-04T08:03:31.202Z",
        "end": "2015-02-04T08:08:44.295Z",
        "distance": 1.928250095717729
      }
    ]
  },
  {
    "key": "1065",
    "values": [
      {
        "teamid": "1065",
        "method": "public_transport",
        "start": "2015-02-02T11:23:22.148Z",
        "end": "2015-02-02T11:29:18.576Z",
        "distance": 3.977075983406294
      },
      {
        "teamid": "1065",
        "method": "public_transport",
        "start": "2015-02-02T11:38:16.645Z",
        "end": "2015-02-02T11:45:41.963Z",
        "distance": 1.9875613234319605
      },
      {
        "teamid": "1065",
        "method": "walking",
        "start": "2015-02-02T11:46:28.883Z",
        "end": "2015-02-02T11:52:24.945Z",
        "distance": 0.5339816916543855
      },
      {
        "teamid": "1065",
        "method": "walking",
        "start": "2015-02-02T12:23:04.455Z",
        "end": "2015-02-02T12:24:14.753Z",
        "distance": 0.2294538648844692
      }
    ]
  },
  {
    "key": "1067",
    "values": [
      {
        "teamid": "1067",
        "method": "public_transport",
        "start": "2015-02-03T10:51:15.094Z",
        "end": "2015-02-03T13:15:17.016Z",
        "distance": 18.22692955727586
      },
      {
        "teamid": "1067",
        "method": "public_transport",
        "start": "2015-02-04T21:25:10.177Z",
        "end": "2015-02-04T21:25:35.081Z",
        "distance": 4.097700301947906
      },
      {
        "teamid": "1067",
        "method": "public_transport",
        "start": "2015-02-04T21:27:47.551Z",
        "end": "2015-02-04T21:28:06.129Z",
        "distance": 19.68048595262035
      },
      {
        "teamid": "1067",
        "method": "public_transport",
        "start": "2015-02-04T21:28:44.616Z",
        "end": "2015-02-04T21:29:41.109Z",
        "distance": 15.936880430813824
      },
      {
        "teamid": "1067",
        "method": "public_transport",
        "start": "2015-02-05T15:52:57.356Z",
        "end": "2015-02-05T15:53:13.441Z",
        "distance": 5.721444814212461
      }
    ]
  },
  {
    "key": "1070",
    "values": [
      {
        "teamid": "1070",
        "method": "walking",
        "start": "2015-02-03T08:20:09.582Z",
        "end": "2015-02-03T08:29:49.642Z",
        "distance": 0.8486096511510562
      }
    ]
  },
  {
    "key": "1073",
    "values": [
      {
        "teamid": "1073",
        "method": "walking",
        "start": "2015-02-03T12:02:36.070Z",
        "end": "2015-02-03T12:12:40.074Z",
        "distance": 1.4305384125810838
      }
    ]
  },
  {
    "key": "1074",
    "values": [
      {
        "teamid": "1074",
        "method": "public_transport",
        "start": "2015-02-05T09:37:25.511Z",
        "end": "2015-02-05T10:20:15.046Z",
        "distance": 259.55128101093794
      },
      {
        "teamid": "1074",
        "method": "walking",
        "start": "2015-02-05T10:20:22.699Z",
        "end": "2015-02-05T10:26:49.433Z",
        "distance": 1.2029838236757513
      },
      {
        "teamid": "1074",
        "method": "walking",
        "start": "2015-02-05T11:14:49.722Z",
        "end": "2015-02-05T11:21:30.728Z",
        "distance": 0.6684250387127881
      },
      {
        "teamid": "1074",
        "method": "public_transport",
        "start": "2015-02-05T12:03:16.946Z",
        "end": "2015-02-05T12:03:48.726Z",
        "distance": 1.8949367451402792
      }
    ]
  },
  {
    "key": "1076",
    "values": [
      {
        "teamid": "1076",
        "method": "public_transport",
        "start": "2015-02-02T09:39:45.180Z",
        "end": "2015-02-02T09:59:08.068Z",
        "distance": 3.9647148450592753
      }
    ]
  },
  {
    "key": "1078",
    "values": [
      {
        "teamid": "1078",
        "method": "walking",
        "start": "2015-02-03T13:27:35.533Z",
        "end": "2015-02-03T13:30:47.609Z",
        "distance": 0.21432808438144846
      },
      {
        "teamid": "1078",
        "method": "public_transport",
        "start": "2015-02-03T13:30:55.604Z",
        "end": "2015-02-03T13:32:29.587Z",
        "distance": 0.23346207726508714
      },
      {
        "teamid": "1078",
        "method": "public_transport",
        "start": "2015-02-03T13:32:35.016Z",
        "end": "2015-02-03T13:33:46.601Z",
        "distance": 0.29269931857053866
      },
      {
        "teamid": "1078",
        "method": "public_transport",
        "start": "2015-02-03T13:34:13.174Z",
        "end": "2015-02-03T13:35:39.588Z",
        "distance": 0.3962073172280631
      },
      {
        "teamid": "1078",
        "method": "public_transport",
        "start": "2015-02-03T13:37:09.602Z",
        "end": "2015-02-03T13:37:34.590Z",
        "distance": 0.21568149879582335
      },
      {
        "teamid": "1078",
        "method": "public_transport",
        "start": "2015-02-03T13:37:46.589Z",
        "end": "2015-02-03T13:38:01.604Z",
        "distance": 0.5127067001053871
      },
      {
        "teamid": "1078",
        "method": "public_transport",
        "start": "2015-02-03T13:38:12.591Z",
        "end": "2015-02-03T13:39:07.601Z",
        "distance": 0.20958655471276685
      },
      {
        "teamid": "1078",
        "method": "public_transport",
        "start": "2015-02-03T13:39:19.600Z",
        "end": "2015-02-03T13:39:45.588Z",
        "distance": 0.47354505244394396
      },
      {
        "teamid": "1078",
        "method": "public_transport",
        "start": "2015-02-03T13:39:58.802Z",
        "end": "2015-02-03T13:40:22.599Z",
        "distance": 0.25546070302708884
      },
      {
        "teamid": "1078",
        "method": "public_transport",
        "start": "2015-02-03T13:40:33.241Z",
        "end": "2015-02-03T13:41:12.596Z",
        "distance": 0.2295751510379188
      },
      {
        "teamid": "1078",
        "method": "walking",
        "start": "2015-02-03T13:42:41.628Z",
        "end": "2015-02-03T13:42:57.593Z",
        "distance": 0.46311244183826045
      }
    ]
  },
  {
    "key": "1079",
    "values": [
      {
        "teamid": "1079",
        "method": "walking",
        "start": "2015-02-02T11:52:42.518Z",
        "end": "2015-02-02T12:27:27.646Z",
        "distance": 1.865910506825638
      }
    ]
  },
  {
    "key": "1088",
    "values": [
      {
        "teamid": "1088",
        "method": "public_transport",
        "start": "2015-02-03T12:46:25.815Z",
        "end": "2015-02-03T13:14:09.191Z",
        "distance": 5.25274380907426
      }
    ]
  },
  {
    "key": "1089",
    "values": [
      {
        "teamid": "1089",
        "method": "walking",
        "start": "2015-02-02T10:39:32.620Z",
        "end": "2015-02-02T11:08:53.893Z",
        "distance": 0.7529538248532991
      }
    ]
  },
  {
    "key": "1094",
    "values": [
      {
        "teamid": "1094",
        "method": "public_transport",
        "start": "2015-02-03T08:03:35.822Z",
        "end": "2015-02-03T08:25:15.702Z",
        "distance": 3.8576870071994036
      },
      {
        "teamid": "1094",
        "method": "walking",
        "start": "2015-02-03T13:38:38.476Z",
        "end": "2015-02-03T14:15:45.883Z",
        "distance": 4.790819510539338
      },
      {
        "teamid": "1094",
        "method": "walking",
        "start": "2015-02-03T14:15:53.852Z",
        "end": "2015-02-03T14:22:24.383Z",
        "distance": 0.393359369468597
      }
    ]
  },
  {
    "key": "1096",
    "values": [
      {
        "teamid": "1096",
        "method": "public_transport",
        "start": "2015-02-02T12:27:11.846Z",
        "end": "2015-02-02T12:33:54.636Z",
        "distance": 4.57674866568753
      }
    ]
  },
  {
    "key": "1097",
    "values": [
      {
        "teamid": "1097",
        "method": "bike",
        "start": "2015-02-04T13:02:49.589Z",
        "end": "2015-02-04T13:03:34.357Z",
        "distance": 0.21252744716120728
      }
    ]
  },
  {
    "key": "1100",
    "values": [
      {
        "teamid": "1100",
        "method": "walking",
        "start": "2015-02-02T09:38:31.476Z",
        "end": "2015-02-02T10:07:40.200Z",
        "distance": 3.0578650973115162
      },
      {
        "teamid": "1100",
        "method": "walking",
        "start": "2015-02-03T14:33:00.500Z",
        "end": "2015-02-03T15:56:17.867Z",
        "distance": 4.098812500233906
      },
      {
        "teamid": "1100",
        "method": "walking",
        "start": "2015-02-05T10:09:23.963Z",
        "end": "2015-02-05T10:44:37.812Z",
        "distance": 3.930906974538031
      }
    ]
  },
  {
    "key": "1104",
    "values": [
      {
        "teamid": "1104",
        "method": "walking",
        "start": "2015-02-02T14:20:06.131Z",
        "end": "2015-02-02T15:21:29.892Z",
        "distance": 4.997653386661321
      }
    ]
  },
  {
    "key": "1106",
    "values": [
      {
        "teamid": "1106",
        "method": "public_transport",
        "start": "2015-02-02T13:08:00.892Z",
        "end": "2015-02-02T13:21:19.000Z",
        "distance": 3.876911288684722
      },
      {
        "teamid": "1106",
        "method": "public_transport",
        "start": "2015-02-02T13:21:25.013Z",
        "end": "2015-02-02T13:57:03.000Z",
        "distance": 12.237986314831788
      },
      {
        "teamid": "1106",
        "method": "walking",
        "start": "2015-02-02T13:57:13.000Z",
        "end": "2015-02-02T14:14:28.000Z",
        "distance": 1.2075035839227002
      },
      {
        "teamid": "1106",
        "method": "public_transport",
        "start": "2015-02-04T08:06:42.739Z",
        "end": "2015-02-04T09:49:02.000Z",
        "distance": 26.180653229694766
      }
    ]
  },
  {
    "key": "1107",
    "values": [
      {
        "teamid": "1107",
        "method": "walking",
        "start": "2015-02-02T11:01:53.946Z",
        "end": "2015-02-02T11:56:57.716Z",
        "distance": 1.7609823219969385
      },
      {
        "teamid": "1107",
        "method": "walking",
        "start": "2015-02-02T11:02:20.610Z",
        "end": "2015-02-02T12:04:33.316Z",
        "distance": 0.9711292794764234
      },
      {
        "teamid": "1107",
        "method": "walking",
        "start": "2015-02-02T13:00:09.223Z",
        "end": "2015-02-02T13:19:45.561Z",
        "distance": 1.5655300565954409
      },
      {
        "teamid": "1107",
        "method": "public_transport",
        "start": "2015-02-02T13:26:59.455Z",
        "end": "2015-02-02T14:15:36.879Z",
        "distance": 46.24705546856056
      },
      {
        "teamid": "1107",
        "method": "walking",
        "start": "2015-02-03T13:58:47.433Z",
        "end": "2015-02-03T14:07:59.323Z",
        "distance": 7.287451140568772
      },
      {
        "teamid": "1107",
        "method": "walking",
        "start": "2015-02-03T14:10:06.358Z",
        "end": "2015-02-03T14:39:10.183Z",
        "distance": 2.1242941455926347
      }
    ]
  },
  {
    "key": "1108",
    "values": [
      {
        "teamid": "1108",
        "method": "walking",
        "start": "2015-02-03T08:02:48.169Z",
        "end": "2015-02-03T08:38:15.531Z",
        "distance": 12.815796146535883
      },
      {
        "teamid": "1108",
        "method": "walking",
        "start": "2015-02-03T09:45:01.963Z",
        "end": "2015-02-03T10:15:00.279Z",
        "distance": 6.475612612853098
      }
    ]
  },
  {
    "key": "1109",
    "values": [
      {
        "teamid": "1109",
        "method": "public_transport",
        "start": "2015-02-02T12:26:36.949Z",
        "end": "2015-02-02T13:11:25.878Z",
        "distance": 5.925996955060955
      },
      {
        "teamid": "1109",
        "method": "public_transport",
        "start": "2015-02-02T13:43:52.783Z",
        "end": "2015-02-02T14:06:14.868Z",
        "distance": 3.6943002361832784
      },
      {
        "teamid": "1109",
        "method": "public_transport",
        "start": "2015-02-02T14:06:24.818Z",
        "end": "2015-02-02T14:24:55.960Z",
        "distance": 9.775608639965592
      },
      {
        "teamid": "1109",
        "method": "bike",
        "start": "2015-02-03T09:01:30.905Z",
        "end": "2015-02-03T10:32:10.497Z",
        "distance": 6.877998888342326
      },
      {
        "teamid": "1109",
        "method": "public_transport",
        "start": "2015-02-04T13:17:25.937Z",
        "end": "2015-02-04T13:40:24.180Z",
        "distance": 67.43318365145723
      },
      {
        "teamid": "1109",
        "method": "walking",
        "start": "2015-02-04T13:40:38.290Z",
        "end": "2015-02-04T14:08:12.506Z",
        "distance": 1.3638002636048636
      }
    ]
  },
  {
    "key": "1113",
    "values": [
      {
        "teamid": "1113",
        "method": "walking",
        "start": "2015-02-02T12:37:50.147Z",
        "end": "2015-02-02T12:45:35.858Z",
        "distance": 0.32362868823631047
      }
    ]
  },
  {
    "key": "1119",
    "values": [
      {
        "teamid": "1119",
        "method": "walking",
        "start": "2015-02-02T12:12:18.945Z",
        "end": "2015-02-02T12:38:05.192Z",
        "distance": 29.398785926417542
      },
      {
        "teamid": "1119",
        "method": "walking",
        "start": "2015-02-02T12:38:09.844Z",
        "end": "2015-02-02T12:51:37.808Z",
        "distance": 1.8126670822351236
      },
      {
        "teamid": "1119",
        "method": "public_transport",
        "start": "2015-02-02T13:34:15.000Z",
        "end": "2015-02-02T14:14:29.000Z",
        "distance": 8.48080229462647
      }
    ]
  },
  {
    "key": "1120",
    "values": [
      {
        "teamid": "1120",
        "method": "walking",
        "start": "2015-02-04T13:24:07.023Z",
        "end": "2015-02-04T13:31:36.092Z",
        "distance": 0.7350900336960404
      },
      {
        "teamid": "1120",
        "method": "bike",
        "start": "2015-02-04T13:35:21.882Z",
        "end": "2015-02-04T13:47:24.103Z",
        "distance": 1.0698469656847673
      }
    ]
  },
  {
    "key": "1122",
    "values": [
      {
        "teamid": "1122",
        "method": "public_transport",
        "start": "2015-02-02T10:19:21.708Z",
        "end": "2015-02-02T10:21:51.711Z",
        "distance": 0.7435082288817431
      }
    ]
  },
  {
    "key": "1123",
    "values": [
      {
        "teamid": "1123",
        "method": "public_transport",
        "start": "2015-02-03T09:33:23.043Z",
        "end": "2015-02-03T09:42:03.000Z",
        "distance": 0.2144635297646772
      }
    ]
  },
  {
    "key": "1124",
    "values": [
      {
        "teamid": "1124",
        "method": "walking",
        "start": "2015-02-02T13:10:52.341Z",
        "end": "2015-02-02T13:50:34.000Z",
        "distance": 39.937092977031604
      },
      {
        "teamid": "1124",
        "method": "walking",
        "start": "2015-02-03T13:07:19.326Z",
        "end": "2015-02-03T13:09:18.972Z",
        "distance": 3.273227582429817
      },
      {
        "teamid": "1124",
        "method": "walking",
        "start": "2015-02-04T09:34:17.797Z",
        "end": "2015-02-04T09:53:23.835Z",
        "distance": 0.679265077492276
      },
      {
        "teamid": "1124",
        "method": "public_transport",
        "start": "2015-02-05T11:51:09.145Z",
        "end": "2015-02-05T12:06:46.000Z",
        "distance": 6.4277676849069305
      },
      {
        "teamid": "1124",
        "method": "public_transport",
        "start": "2015-02-05T13:00:42.997Z",
        "end": "2015-02-05T13:32:33.000Z",
        "distance": 6.381079748805458
      }
    ]
  },
  {
    "key": "1129",
    "values": [
      {
        "teamid": "1129",
        "method": "walking",
        "start": "2015-02-05T08:31:49.601Z",
        "end": "2015-02-05T08:49:46.716Z",
        "distance": 1.7006551470350095
      },
      {
        "teamid": "1129",
        "method": "walking",
        "start": "2015-02-05T14:40:52.481Z",
        "end": "2015-02-05T16:02:51.128Z",
        "distance": 6.2477872980041
      }
    ]
  },
  {
    "key": "1130",
    "values": [
      {
        "teamid": "1130",
        "method": "public_transport",
        "start": "2015-02-03T15:10:46.666Z",
        "end": "2015-02-03T15:16:21.414Z",
        "distance": 0.3007419994601972
      },
      {
        "teamid": "1130",
        "method": "public_transport",
        "start": "2015-02-03T15:29:12.519Z",
        "end": "2015-02-03T16:16:11.447Z",
        "distance": 356.7277999003135
      },
      {
        "teamid": "1130",
        "method": "walking",
        "start": "2015-02-03T16:16:18.926Z",
        "end": "2015-02-03T17:04:23.055Z",
        "distance": 143.60469665066123
      },
      {
        "teamid": "1130",
        "method": "walking",
        "start": "2015-02-04T08:28:58.405Z",
        "end": "2015-02-04T08:33:06.611Z",
        "distance": 0.474757044032861
      },
      {
        "teamid": "1130",
        "method": "walking",
        "start": "2015-02-04T12:09:05.786Z",
        "end": "2015-02-04T12:34:00.574Z",
        "distance": 1.1517657248834583
      },
      {
        "teamid": "1130",
        "method": "walking",
        "start": "2015-02-04T14:57:05.528Z",
        "end": "2015-02-04T15:39:54.726Z",
        "distance": 50.778513857930136
      }
    ]
  },
  {
    "key": "1131",
    "values": [
      {
        "teamid": "1131",
        "method": "walking",
        "start": "2015-02-03T12:42:00.595Z",
        "end": "2015-02-03T14:37:24.611Z",
        "distance": 3.35246505426506
      },
      {
        "teamid": "1131",
        "method": "public_transport",
        "start": "2015-02-04T07:33:12.729Z",
        "end": "2015-02-04T07:51:04.735Z",
        "distance": 44.00564761069862
      },
      {
        "teamid": "1131",
        "method": "public_transport",
        "start": "2015-02-04T08:00:20.229Z",
        "end": "2015-02-04T08:19:45.685Z",
        "distance": 7.264602074049775
      },
      {
        "teamid": "1131",
        "method": "walking",
        "start": "2015-02-04T12:49:44.778Z",
        "end": "2015-02-04T13:05:34.655Z",
        "distance": 3.898293449563963
      }
    ]
  },
  {
    "key": "1139",
    "values": [
      {
        "teamid": "1139",
        "method": "public_transport",
        "start": "2015-02-05T09:31:54.297Z",
        "end": "2015-02-05T09:54:30.533Z",
        "distance": 24.738383569592653
      },
      {
        "teamid": "1139",
        "method": "public_transport",
        "start": "2015-02-05T10:04:09.000Z",
        "end": "2015-02-05T10:15:31.000Z",
        "distance": 3.1843647609226142
      }
    ]
  },
  {
    "key": "1142",
    "values": [
      {
        "teamid": "1142",
        "method": "public_transport",
        "start": "2015-02-02T11:33:55.595Z",
        "end": "2015-02-02T11:47:49.999Z",
        "distance": 1.574059824394908
      },
      {
        "teamid": "1142",
        "method": "public_transport",
        "start": "2015-02-02T11:48:21.978Z",
        "end": "2015-02-02T12:20:21.000Z",
        "distance": 2.2727412712336283
      }
    ]
  },
  {
    "key": "1144",
    "values": [
      {
        "teamid": "1144",
        "method": "walking",
        "start": "2015-02-03T13:17:26.912Z",
        "end": "2015-02-03T13:27:18.427Z",
        "distance": 0.5335472151422102
      },
      {
        "teamid": "1144",
        "method": "bike",
        "start": "2015-02-04T14:05:02.729Z",
        "end": "2015-02-04T14:06:56.977Z",
        "distance": 2.2780734508877094
      },
      {
        "teamid": "1144",
        "method": "bike",
        "start": "2015-02-04T14:07:41.267Z",
        "end": "2015-02-04T14:08:41.447Z",
        "distance": 0.3065443029679705
      },
      {
        "teamid": "1144",
        "method": "bike",
        "start": "2015-02-04T14:08:53.535Z",
        "end": "2015-02-04T14:10:11.165Z",
        "distance": 7.820374641289083
      },
      {
        "teamid": "1144",
        "method": "public_transport",
        "start": "2015-02-04T14:10:17.138Z",
        "end": "2015-02-04T14:10:56.909Z",
        "distance": 2.4323682779794926
      },
      {
        "teamid": "1144",
        "method": "public_transport",
        "start": "2015-02-04T14:12:23.641Z",
        "end": "2015-02-04T14:13:19.330Z",
        "distance": 2.7459770022715135
      },
      {
        "teamid": "1144",
        "method": "public_transport",
        "start": "2015-02-04T14:13:37.490Z",
        "end": "2015-02-04T14:15:57.306Z",
        "distance": 92.64178236404223
      },
      {
        "teamid": "1144",
        "method": "bike",
        "start": "2015-02-04T14:16:19.556Z",
        "end": "2015-02-04T14:17:36.446Z",
        "distance": 82.91241655144766
      },
      {
        "teamid": "1144",
        "method": "public_transport",
        "start": "2015-02-05T11:27:35.172Z",
        "end": "2015-02-05T11:31:45.966Z",
        "distance": 1.0338086983455195
      },
      {
        "teamid": "1144",
        "method": "public_transport",
        "start": "2015-02-05T11:31:56.070Z",
        "end": "2015-02-05T11:35:37.748Z",
        "distance": 0.8511819342386372
      }
    ]
  },
  {
    "key": "1146",
    "values": [
      {
        "teamid": "1146",
        "method": "walking",
        "start": "2015-02-04T14:57:20.801Z",
        "end": "2015-02-04T14:57:51.973Z",
        "distance": 8.329727341027498
      },
      {
        "teamid": "1146",
        "method": "walking",
        "start": "2015-02-04T14:57:59.960Z",
        "end": "2015-02-04T14:58:14.963Z",
        "distance": 0.21843438819828317
      },
      {
        "teamid": "1146",
        "method": "walking",
        "start": "2015-02-04T14:58:24.950Z",
        "end": "2015-02-04T15:40:22.746Z",
        "distance": 5.940348193448849
      },
      {
        "teamid": "1146",
        "method": "walking",
        "start": "2015-02-04T15:40:26.298Z",
        "end": "2015-02-04T15:40:38.734Z",
        "distance": 0.2094801701967456
      }
    ]
  },
  {
    "key": "1148",
    "values": [
      {
        "teamid": "1148",
        "method": "walking",
        "start": "2015-02-03T12:41:28.059Z",
        "end": "2015-02-03T12:55:17.487Z",
        "distance": 1.6612312799541362
      },
      {
        "teamid": "1148",
        "method": "public_transport",
        "start": "2015-02-03T14:20:22.488Z",
        "end": "2015-02-03T14:56:06.730Z",
        "distance": 48.407626091533764
      },
      {
        "teamid": "1148",
        "method": "public_transport",
        "start": "2015-02-04T11:42:25.477Z",
        "end": "2015-02-04T11:51:58.629Z",
        "distance": 2.460780769034538
      },
      {
        "teamid": "1148",
        "method": "walking",
        "start": "2015-02-04T11:52:05.101Z",
        "end": "2015-02-04T12:41:29.624Z",
        "distance": 1.7094865267638377
      },
      {
        "teamid": "1148",
        "method": "public_transport",
        "start": "2015-02-04T12:41:40.608Z",
        "end": "2015-02-04T13:49:39.790Z",
        "distance": 2.90583427111467
      },
      {
        "teamid": "1148",
        "method": "public_transport",
        "start": "2015-02-04T15:30:00.618Z",
        "end": "2015-02-04T16:27:21.611Z",
        "distance": 232.28354542803666
      },
      {
        "teamid": "1148",
        "method": "bike",
        "start": "2015-02-04T16:27:34.610Z",
        "end": "2015-02-04T17:01:29.604Z",
        "distance": 6.372885038937829
      },
      {
        "teamid": "1148",
        "method": "public_transport",
        "start": "2015-02-05T08:37:16.417Z",
        "end": "2015-02-05T09:19:17.478Z",
        "distance": 54.24357880731728
      },
      {
        "teamid": "1148",
        "method": "public_transport",
        "start": "2015-02-05T09:27:51.356Z",
        "end": "2015-02-05T09:39:52.486Z",
        "distance": 11.90967350604614
      },
      {
        "teamid": "1148",
        "method": "walking",
        "start": "2015-02-05T11:16:08.551Z",
        "end": "2015-02-05T11:20:29.574Z",
        "distance": 0.506702001523109
      },
      {
        "teamid": "1148",
        "method": "public_transport",
        "start": "2015-02-05T11:23:22.853Z",
        "end": "2015-02-05T11:28:53.387Z",
        "distance": 7.485740766974244
      },
      {
        "teamid": "1148",
        "method": "walking",
        "start": "2015-02-05T11:29:05.678Z",
        "end": "2015-02-05T11:32:48.473Z",
        "distance": 0.2891076031682528
      },
      {
        "teamid": "1148",
        "method": "public_transport",
        "start": "2015-02-05T11:39:13.541Z",
        "end": "2015-02-05T12:24:20.481Z",
        "distance": 61.16796999634552
      }
    ]
  },
  {
    "key": "1155",
    "values": [
      {
        "teamid": "1155",
        "method": "public_transport",
        "start": "2015-02-04T14:17:23.039Z",
        "end": "2015-02-04T14:17:52.000Z",
        "distance": 0.35662440080969315
      }
    ]
  },
  {
    "key": "1161",
    "values": [
      {
        "teamid": "1161",
        "method": "walking",
        "start": "2015-02-02T11:49:23.907Z",
        "end": "2015-02-02T12:09:48.000Z",
        "distance": 8.204972597319312
      },
      {
        "teamid": "1161",
        "method": "walking",
        "start": "2015-02-02T12:29:27.321Z",
        "end": "2015-02-02T13:15:58.000Z",
        "distance": 3.8850343157703153
      }
    ]
  },
  {
    "key": "1164",
    "values": [
      {
        "teamid": "1164",
        "method": "walking",
        "start": "2015-02-04T10:21:48.176Z",
        "end": "2015-02-04T11:14:25.859Z",
        "distance": 0.9139477187759498
      }
    ]
  },
  {
    "key": "1169",
    "values": [
      {
        "teamid": "1169",
        "method": "public_transport",
        "start": "2015-02-05T12:22:25.000Z",
        "end": "2015-02-05T12:24:05.000Z",
        "distance": 0.21209202043509467
      },
      {
        "teamid": "1169",
        "method": "public_transport",
        "start": "2015-02-05T12:24:15.000Z",
        "end": "2015-02-05T12:38:32.000Z",
        "distance": 3.5364465219790384
      },
      {
        "teamid": "1169",
        "method": "public_transport",
        "start": "2015-02-05T12:38:39.000Z",
        "end": "2015-02-05T13:08:31.000Z",
        "distance": 6.207642067383905
      }
    ]
  },
  {
    "key": "1170",
    "values": [
      {
        "teamid": "1170",
        "method": "public_transport",
        "start": "2015-02-04T13:20:48.434Z",
        "end": "2015-02-04T13:30:12.895Z",
        "distance": 0.4810103826724298
      }
    ]
  },
  {
    "key": "1171",
    "values": [
      {
        "teamid": "1171",
        "method": "public_transport",
        "start": "2015-02-03T11:04:24.262Z",
        "end": "2015-02-03T11:10:33.129Z",
        "distance": 1.3268726356206384
      }
    ]
  },
  {
    "key": "1178",
    "values": [
      {
        "teamid": "1178",
        "method": "public_transport",
        "start": "2015-02-03T12:46:13.655Z",
        "end": "2015-02-03T13:08:14.788Z",
        "distance": 4.797023638251996
      },
      {
        "teamid": "1178",
        "method": "walking",
        "start": "2015-02-03T13:09:04.212Z",
        "end": "2015-02-03T13:13:15.208Z",
        "distance": 0.2634472870873681
      }
    ]
  },
  {
    "key": "1180",
    "values": [
      {
        "teamid": "1180",
        "method": "public_transport",
        "start": "2015-02-03T09:23:39.308Z",
        "end": "2015-02-03T09:36:57.000Z",
        "distance": 47.02462853575779
      },
      {
        "teamid": "1180",
        "method": "walking",
        "start": "2015-02-03T09:47:14.259Z",
        "end": "2015-02-03T09:49:32.000Z",
        "distance": 1.403296762638928
      },
      {
        "teamid": "1180",
        "method": "walking",
        "start": "2015-02-03T10:00:03.913Z",
        "end": "2015-02-03T10:15:04.734Z",
        "distance": 11.426343042830771
      },
      {
        "teamid": "1180",
        "method": "walking",
        "start": "2015-02-03T11:08:56.609Z",
        "end": "2015-02-03T11:21:12.000Z",
        "distance": 12.57705758147868
      },
      {
        "teamid": "1180",
        "method": "walking",
        "start": "2015-02-03T14:50:36.629Z",
        "end": "2015-02-03T14:52:38.000Z",
        "distance": 0.506098823976863
      },
      {
        "teamid": "1180",
        "method": "walking",
        "start": "2015-02-03T15:01:20.642Z",
        "end": "2015-02-03T15:04:03.000Z",
        "distance": 1.407337139492265
      },
      {
        "teamid": "1180",
        "method": "public_transport",
        "start": "2015-02-03T15:13:22.088Z",
        "end": "2015-02-03T15:17:46.000Z",
        "distance": 6.694340184429497
      },
      {
        "teamid": "1180",
        "method": "walking",
        "start": "2015-02-04T08:34:48.291Z",
        "end": "2015-02-04T08:54:30.036Z",
        "distance": 26.671342368273553
      },
      {
        "teamid": "1180",
        "method": "walking",
        "start": "2015-02-04T08:54:45.012Z",
        "end": "2015-02-04T09:07:10.399Z",
        "distance": 7.209813263392016
      },
      {
        "teamid": "1180",
        "method": "public_transport",
        "start": "2015-02-04T12:32:31.754Z",
        "end": "2015-02-04T13:04:42.713Z",
        "distance": 46.32729567967685
      },
      {
        "teamid": "1180",
        "method": "public_transport",
        "start": "2015-02-04T13:04:47.940Z",
        "end": "2015-02-04T13:05:17.745Z",
        "distance": 1.2392243391437234
      }
    ]
  },
  {
    "key": "1184",
    "values": [
      {
        "teamid": "1184",
        "method": "walking",
        "start": "2015-02-02T13:12:54.290Z",
        "end": "2015-02-02T13:34:35.000Z",
        "distance": 7.254109793379326
      },
      {
        "teamid": "1184",
        "method": "walking",
        "start": "2015-02-02T13:13:00.746Z",
        "end": "2015-02-02T13:18:16.392Z",
        "distance": 0.22685974755272964
      },
      {
        "teamid": "1184",
        "method": "walking",
        "start": "2015-02-02T13:14:15.856Z",
        "end": "2015-02-02T13:21:47.291Z",
        "distance": 0.727460374149881
      },
      {
        "teamid": "1184",
        "method": "walking",
        "start": "2015-02-02T13:17:34.652Z",
        "end": "2015-02-02T13:53:16.972Z",
        "distance": 11.540928925870649
      },
      {
        "teamid": "1184",
        "method": "public_transport",
        "start": "2015-02-02T13:23:09.043Z",
        "end": "2015-02-02T13:56:14.992Z",
        "distance": 10.023521393056438
      },
      {
        "teamid": "1184",
        "method": "public_transport",
        "start": "2015-02-02T13:46:49.797Z",
        "end": "2015-02-02T13:54:23.929Z",
        "distance": 2.7087709532004376
      }
    ]
  },
  {
    "key": "1196",
    "values": [
      {
        "teamid": "1196",
        "method": "walking",
        "start": "2015-02-04T14:20:37.110Z",
        "end": "2015-02-04T14:21:09.000Z",
        "distance": 0.2632779765075206
      },
      {
        "teamid": "1196",
        "method": "walking",
        "start": "2015-02-04T14:21:15.908Z",
        "end": "2015-02-04T14:21:38.000Z",
        "distance": 0.32559167401971706
      },
      {
        "teamid": "1196",
        "method": "walking",
        "start": "2015-02-04T14:22:25.720Z",
        "end": "2015-02-04T14:23:08.000Z",
        "distance": 0.23005199965688725
      },
      {
        "teamid": "1196",
        "method": "walking",
        "start": "2015-02-04T14:23:18.629Z",
        "end": "2015-02-04T14:23:42.000Z",
        "distance": 0.21519524559805067
      },
      {
        "teamid": "1196",
        "method": "walking",
        "start": "2015-02-04T16:16:04.248Z",
        "end": "2015-02-04T16:17:43.994Z",
        "distance": 0.7205278548034713
      },
      {
        "teamid": "1196",
        "method": "walking",
        "start": "2015-02-04T16:17:57.879Z",
        "end": "2015-02-04T16:19:41.758Z",
        "distance": 1.2423258270235198
      },
      {
        "teamid": "1196",
        "method": "walking",
        "start": "2015-02-04T16:19:59.557Z",
        "end": "2015-02-04T16:47:39.000Z",
        "distance": 11.036052866415332
      }
    ]
  },
  {
    "key": "1198",
    "values": [
      {
        "teamid": "1198",
        "method": "public_transport",
        "start": "2015-02-03T13:40:29.463Z",
        "end": "2015-02-03T13:44:03.446Z",
        "distance": 0.22774250367681495
      },
      {
        "teamid": "1198",
        "method": "walking",
        "start": "2015-02-03T13:44:53.315Z",
        "end": "2015-02-03T13:51:09.686Z",
        "distance": 0.7046086755127602
      },
      {
        "teamid": "1198",
        "method": "walking",
        "start": "2015-02-03T13:55:34.640Z",
        "end": "2015-02-03T13:59:19.921Z",
        "distance": 0.32308409987389586
      }
    ]
  },
  {
    "key": "1199",
    "values": [
      {
        "teamid": "1199",
        "method": "walking",
        "start": "2015-02-04T11:52:35.279Z",
        "end": "2015-02-04T12:12:33.497Z",
        "distance": 1.9609997007299313
      }
    ]
  },
  {
    "key": "1200",
    "values": [
      {
        "teamid": "1200",
        "method": "public_transport",
        "start": "2015-02-05T09:14:27.298Z",
        "end": "2015-02-05T09:31:44.000Z",
        "distance": 3.0788731802353637
      }
    ]
  },
  {
    "key": "1209",
    "values": [
      {
        "teamid": "1209",
        "method": "public_transport",
        "start": "2015-02-04T11:53:50.221Z",
        "end": "2015-02-04T14:17:05.302Z",
        "distance": 1.3125103334283719
      }
    ]
  },
  {
    "key": "1210",
    "values": [
      {
        "teamid": "1210",
        "method": "walking",
        "start": "2015-02-02T10:35:03.999Z",
        "end": "2015-02-02T10:41:54.999Z",
        "distance": 2.01142605198121
      },
      {
        "teamid": "1210",
        "method": "walking",
        "start": "2015-02-03T08:46:27.675Z",
        "end": "2015-02-03T09:01:53.000Z",
        "distance": 2.2221053153568415
      },
      {
        "teamid": "1210",
        "method": "walking",
        "start": "2015-02-03T09:38:36.480Z",
        "end": "2015-02-03T10:22:35.000Z",
        "distance": 3.9905484664829896
      },
      {
        "teamid": "1210",
        "method": "walking",
        "start": "2015-02-04T12:37:37.366Z",
        "end": "2015-02-04T13:45:46.000Z",
        "distance": 9.276932181665975
      }
    ]
  },
  {
    "key": "1213",
    "values": [
      {
        "teamid": "1213",
        "method": "public_transport",
        "start": "2015-02-03T08:57:13.942Z",
        "end": "2015-02-03T09:04:59.263Z",
        "distance": 6.458366573915096
      }
    ]
  },
  {
    "key": "1219",
    "values": [
      {
        "teamid": "1219",
        "method": "walking",
        "start": "2015-02-02T12:48:04.780Z",
        "end": "2015-02-02T12:51:56.243Z",
        "distance": 0.6359093864079677
      }
    ]
  },
  {
    "key": "1226",
    "values": [
      {
        "teamid": "1226",
        "method": "walking",
        "start": "2015-02-02T10:29:07.000Z",
        "end": "2015-02-02T10:31:35.000Z",
        "distance": 0.21381787431027227
      }
    ]
  },
  {
    "key": "1227",
    "values": [
      {
        "teamid": "1227",
        "method": "walking",
        "start": "2015-02-02T09:48:57.518Z",
        "end": "2015-02-02T10:17:24.443Z",
        "distance": 5.3410036035320125
      },
      {
        "teamid": "1227",
        "method": "public_transport",
        "start": "2015-02-03T12:24:40.418Z",
        "end": "2015-02-03T12:48:38.882Z",
        "distance": 4.294548274595383
      }
    ]
  },
  {
    "key": "1228",
    "values": [
      {
        "teamid": "1228",
        "method": "walking",
        "start": "2015-02-03T13:46:10.145Z",
        "end": "2015-02-03T13:56:03.000Z",
        "distance": 2.6227419653719135
      }
    ]
  },
  {
    "key": "1234",
    "values": [
      {
        "teamid": "1234",
        "method": "public_transport",
        "start": "2015-02-02T11:31:37.535Z",
        "end": "2015-02-02T11:42:38.820Z",
        "distance": 2.479419050837707
      },
      {
        "teamid": "1234",
        "method": "public_transport",
        "start": "2015-02-02T12:39:14.328Z",
        "end": "2015-02-02T14:11:41.876Z",
        "distance": 51.980438009077
      }
    ]
  },
  {
    "key": "1235",
    "values": [
      {
        "teamid": "1235",
        "method": "public_transport",
        "start": "2015-02-03T14:41:59.568Z",
        "end": "2015-02-03T14:53:42.441Z",
        "distance": 9.897281165633522
      }
    ]
  },
  {
    "key": "1236",
    "values": [
      {
        "teamid": "1236",
        "method": "walking",
        "start": "2015-02-04T14:04:43.454Z",
        "end": "2015-02-04T14:26:34.712Z",
        "distance": 1.8627743459373287
      }
    ]
  },
  {
    "key": "1238",
    "values": [
      {
        "teamid": "1238",
        "method": "bike",
        "start": "2015-02-03T10:55:39.933Z",
        "end": "2015-02-03T11:04:04.469Z",
        "distance": 1.0704153472104767
      },
      {
        "teamid": "1238",
        "method": "walking",
        "start": "2015-02-03T16:44:46.474Z",
        "end": "2015-02-03T17:11:47.000Z",
        "distance": 9.057257484000738
      },
      {
        "teamid": "1238",
        "method": "bike",
        "start": "2015-02-03T17:20:13.346Z",
        "end": "2015-02-03T17:45:44.090Z",
        "distance": 17.57462318485685
      }
    ]
  },
  {
    "key": "1241",
    "values": [
      {
        "teamid": "1241",
        "method": "public_transport",
        "start": "2015-02-03T10:50:47.925Z",
        "end": "2015-02-03T11:23:16.000Z",
        "distance": 6.824703996378477
      },
      {
        "teamid": "1241",
        "method": "public_transport",
        "start": "2015-02-04T07:11:33.910Z",
        "end": "2015-02-04T07:37:28.000Z",
        "distance": 5.584661390106199
      },
      {
        "teamid": "1241",
        "method": "public_transport",
        "start": "2015-02-04T07:45:31.246Z",
        "end": "2015-02-04T07:57:54.000Z",
        "distance": 2.8136644747045363
      }
    ]
  },
  {
    "key": "1244",
    "values": [
      {
        "teamid": "1244",
        "method": "public_transport",
        "start": "2015-02-04T13:20:49.726Z",
        "end": "2015-02-04T13:26:53.656Z",
        "distance": 4.022630332278043
      },
      {
        "teamid": "1244",
        "method": "walking",
        "start": "2015-02-05T11:32:38.077Z",
        "end": "2015-02-05T11:36:50.199Z",
        "distance": 0.6282568594535085
      }
    ]
  },
  {
    "key": "1252",
    "values": [
      {
        "teamid": "1252",
        "method": "public_transport",
        "start": "2015-02-05T14:50:13.687Z",
        "end": "2015-02-05T14:53:22.829Z",
        "distance": 0.8198035128773323
      }
    ]
  },
  {
    "key": "1253",
    "values": [
      {
        "teamid": "1253",
        "method": "public_transport",
        "start": "2015-02-02T12:11:01.816Z",
        "end": "2015-02-02T12:26:28.498Z",
        "distance": 9.095292660400501
      },
      {
        "teamid": "1253",
        "method": "walking",
        "start": "2015-02-02T12:26:32.918Z",
        "end": "2015-02-02T13:24:06.865Z",
        "distance": 1.4500980437646787
      },
      {
        "teamid": "1253",
        "method": "public_transport",
        "start": "2015-02-02T13:24:47.187Z",
        "end": "2015-02-02T13:38:19.323Z",
        "distance": 7.1924671200846495
      },
      {
        "teamid": "1253",
        "method": "public_transport",
        "start": "2015-02-03T12:20:40.591Z",
        "end": "2015-02-03T12:43:32.274Z",
        "distance": 9.781714325825236
      },
      {
        "teamid": "1253",
        "method": "walking",
        "start": "2015-02-03T12:44:31.551Z",
        "end": "2015-02-03T12:50:03.289Z",
        "distance": 0.6542260597597187
      },
      {
        "teamid": "1253",
        "method": "public_transport",
        "start": "2015-02-03T13:34:30.187Z",
        "end": "2015-02-03T14:30:54.683Z",
        "distance": 15.221243662373483
      }
    ]
  },
  {
    "key": "1256",
    "values": [
      {
        "teamid": "1256",
        "method": "public_transport",
        "start": "2015-02-04T11:53:19.057Z",
        "end": "2015-02-04T11:59:06.925Z",
        "distance": 3.6579474688811695
      }
    ]
  },
  {
    "key": "1257",
    "values": [
      {
        "teamid": "1257",
        "method": "walking",
        "start": "2015-02-02T13:46:20.255Z",
        "end": "2015-02-02T13:58:00.581Z",
        "distance": 19.06795259032913
      },
      {
        "teamid": "1257",
        "method": "bike",
        "start": "2015-02-02T13:57:32.390Z",
        "end": "2015-02-02T17:36:27.998Z",
        "distance": 4.610377644417625
      },
      {
        "teamid": "1257",
        "method": "walking",
        "start": "2015-02-02T13:58:24.463Z",
        "end": "2015-02-02T14:00:18.000Z",
        "distance": 0.36429991985954485
      },
      {
        "teamid": "1257",
        "method": "public_transport",
        "start": "2015-02-02T14:00:28.647Z",
        "end": "2015-02-02T14:20:07.000Z",
        "distance": 36.008335290238044
      },
      {
        "teamid": "1257",
        "method": "walking",
        "start": "2015-02-02T14:20:14.370Z",
        "end": "2015-02-02T14:42:21.000Z",
        "distance": 2.681528331034854
      },
      {
        "teamid": "1257",
        "method": "public_transport",
        "start": "2015-02-02T14:43:29.006Z",
        "end": "2015-02-02T14:50:06.000Z",
        "distance": 9.406126315614177
      },
      {
        "teamid": "1257",
        "method": "walking",
        "start": "2015-02-02T14:50:12.000Z",
        "end": "2015-02-02T15:05:27.000Z",
        "distance": 1.8873867256480474
      },
      {
        "teamid": "1257",
        "method": "walking",
        "start": "2015-02-03T09:11:02.649Z",
        "end": "2015-02-03T09:29:19.000Z",
        "distance": 13.776665959481766
      }
    ]
  },
  {
    "key": "<strong>Henk</strong>",
    "values": [
      {
        "teamid": "<strong>Henk</strong>",
        "method": "public_transport",
        "start": "2015-02-02T15:17:17.553Z",
        "end": "2015-02-02T15:17:35.122Z",
        "distance": 2.185088790091284
      },
      {
        "teamid": "<strong>Henk</strong>",
        "method": "public_transport",
        "start": "2015-02-02T15:17:56.124Z",
        "end": "2015-02-02T15:18:06.125Z",
        "distance": 0.24052891523702719
      },
      {
        "teamid": "<strong>Henk</strong>",
        "method": "public_transport",
        "start": "2015-02-02T15:18:12.124Z",
        "end": "2015-02-02T15:18:28.121Z",
        "distance": 0.44150839546153586
      },
      {
        "teamid": "<strong>Henk</strong>",
        "method": "public_transport",
        "start": "2015-02-02T15:19:26.127Z",
        "end": "2015-02-02T15:19:34.123Z",
        "distance": 4.258329975753288
      },
      {
        "teamid": "<strong>Henk</strong>",
        "method": "public_transport",
        "start": "2015-02-02T15:19:41.124Z",
        "end": "2015-02-02T15:19:53.151Z",
        "distance": 0.41575510484411005
      },
      {
        "teamid": "<strong>Henk</strong>",
        "method": "public_transport",
        "start": "2015-02-02T15:19:58.324Z",
        "end": "2015-02-02T15:20:07.150Z",
        "distance": 0.45505125914001454
      }
    ]
  },
  {
    "key": "1109 ",
    "values": [
      {
        "teamid": "1109 ",
        "method": "walking",
        "start": "2015-02-03T08:31:28.505Z",
        "end": "2015-02-03T11:04:10.342Z",
        "distance": 164.93306965660454
      }
    ]
  },
  {
    "key": "1144 ",
    "values": [
      {
        "teamid": "1144 ",
        "method": "walking",
        "start": "2015-02-04T13:53:32.093Z",
        "end": "2015-02-04T13:54:47.811Z",
        "distance": 0.20610509483864203
      },
      {
        "teamid": "1144 ",
        "method": "walking",
        "start": "2015-02-04T13:54:48.802Z",
        "end": "2015-02-04T13:56:34.403Z",
        "distance": 0.24224914321171429
      },
      {
        "teamid": "1144 ",
        "method": "walking",
        "start": "2015-02-04T13:57:51.075Z",
        "end": "2015-02-04T13:58:12.094Z",
        "distance": 0.2833427454040211
      },
      {
        "teamid": "1144 ",
        "method": "walking",
        "start": "2015-02-04T13:58:15.097Z",
        "end": "2015-02-04T13:59:48.142Z",
        "distance": 2.517134879737819
      },
      {
        "teamid": "1144 ",
        "method": "walking",
        "start": "2015-02-04T13:59:51.143Z",
        "end": "2015-02-04T14:00:36.163Z",
        "distance": 1.7812311992166228
      },
      {
        "teamid": "1144 ",
        "method": "walking",
        "start": "2015-02-05T11:40:18.213Z",
        "end": "2015-02-05T11:43:03.700Z",
        "distance": 0.5457053036985087
      },
      {
        "teamid": "1144 ",
        "method": "walking",
        "start": "2015-02-05T11:43:09.659Z",
        "end": "2015-02-05T11:46:41.496Z",
        "distance": 0.5445166659114713
      }
    ]
  }
]